{
  "headers": {
    "cf-cache-status": "MISS",
    "vary": "Accept-Encoding",
    "report-to": "{\"endpoints\":[{\"url\":\"https:\\/\\/a.nel.cloudflare.com\\/report\\/v3?s=gj9c%2BUJ%2BQCI9cjLmnMqm9ugJxNgIlSy9ScXxJi%2Boj0ju8RuPKVtnSUOaWc3ItVdJj1O%2BmSiKHV3LkhZnNHEWcAhHXMYWCBbbCmVroc5aPlmSVGLJ8Wte%2FBv9ygX2I%2FYXl%2FA%3D\"}],\"group\":\"cf-nel\",\"max_age\":604800}",
    "content-type": "application/javascript; charset=utf-8",
    "cross-origin-resource-policy": "cross-origin",
    "alt-svc": "h3=\":443\"; ma=86400, h3-29=\":443\"; ma=86400",
    "cache-control": "public, max-age=604800, s-maxage=43200",
    "x-served-by": "cache-fra-eddf8230048-FRA, cache-jnb7025-JNB",
    "timing-allow-origin": "*",
    "etag": "W/\"2063c-SixmZrKuRs4c5RoRtU0SDIbHoqg\"",
    "access-control-allow-origin": "*",
    "date": "Sat, 18 Mar 2023 06:45:05 GMT",
    "x-jsd-version-type": "version",
    "server": "cloudflare",
    "cf-ray": "7a9b82b3f987c5c5-SEA",
    "access-control-expose-headers": "*",
    "x-content-type-options": "nosniff",
    "x-jsd-version": "0.3.1",
    "nel": "{\"success_fraction\":0.01,\"report_to\":\"cf-nel\",\"max_age\":604800}",
    "strict-transport-security": "max-age=31536000; includeSubDomains; preload",
    "x-cache": "MISS, MISS"
  },
  "url": "https://cdn.jsdelivr.net/npm/pixi/+esm",
  "now": {
    "secs_since_epoch": 1679121905,
    "nanos_since_epoch": 736686549
  }
}